elastic_opentelemetry_instrumentation_openai-1.1.1.dist-info/licenses/LICENSE
opentelemetry/instrumentation/openai/__init__.py
opentelemetry/instrumentation/openai/environment_variables.py
opentelemetry/instrumentation/openai/helpers.py
opentelemetry/instrumentation/openai/metrics.py
opentelemetry/instrumentation/openai/package.py
opentelemetry/instrumentation/openai/version.py
opentelemetry/instrumentation/openai/wrappers.py
elastic_opentelemetry_instrumentation_openai-1.1.1.dist-info/METADATA
elastic_opentelemetry_instrumentation_openai-1.1.1.dist-info/WHEEL
elastic_opentelemetry_instrumentation_openai-1.1.1.dist-info/entry_points.txt
elastic_opentelemetry_instrumentation_openai-1.1.1.dist-info/top_level.txt
elastic_opentelemetry_instrumentation_openai-1.1.1.dist-info/RECORD
