Metadata-Version: 2.4
Name: elastic-opentelemetry-instrumentation-openai
Version: 1.1.1
Summary: OpenAI Instrumentation Package
Author-email: Riccardo Magliocchetti <riccardo.magliocchetti@elastic.co>
Maintainer-email: Riccardo Magliocchetti <riccardo.magliocchetti@elastic.co>
License:                                  Apache License
Project-URL: Homepage, https://github.com/elastic/elastic-otel-python-instrumentations
Project-URL: Bug Tracker, https://github.com/elastic/elastic-otel-python-instrumentations/issues
Classifier: Development Status :: 3 - Alpha
Classifier: Intended Audience :: Developers
Classifier: Framework :: OpenTelemetry
Classifier: Framework :: OpenTelemetry :: Distros
Classifier: License :: OSI Approved :: Apache Software License
Classifier: Programming Language :: Python
Classifier: Programming Language :: Python :: 3
Classifier: Programming Language :: Python :: 3.8
Classifier: Programming Language :: Python :: 3.9
Classifier: Programming Language :: Python :: 3.10
Classifier: Programming Language :: Python :: 3.11
Classifier: Programming Language :: Python :: 3.12
Classifier: Programming Language :: Python :: 3.13
Requires-Python: >=3.8
License-File: LICENSE
Requires-Dist: opentelemetry-api~=1.31
Requires-Dist: opentelemetry-instrumentation~=0.52b0
Requires-Dist: opentelemetry-semantic-conventions~=0.52b0
Requires-Dist: wrapt<2.0.0,>=1.0.0
Provides-Extra: dev
Requires-Dist: pytest; extra == "dev"
Requires-Dist: pip-tools; extra == "dev"
Requires-Dist: openai; extra == "dev"
Requires-Dist: numpy; extra == "dev"
Requires-Dist: opentelemetry-test-utils; extra == "dev"
Requires-Dist: vcrpy; extra == "dev"
Requires-Dist: pytest-asyncio; extra == "dev"
Requires-Dist: pytest-vcr; extra == "dev"
Requires-Dist: pydantic; extra == "dev"
Provides-Extra: instruments
Requires-Dist: openai>=1.2.0; extra == "instruments"
Dynamic: license-file
